odoo10_addon_sale_order_import_ubl-10.0.1.0.0-py2.7-nspkg.pth
odoo/addons/sale_order_import_ubl/README.rst
odoo/addons/sale_order_import_ubl/__init__.py
odoo/addons/sale_order_import_ubl/__manifest__.py
odoo/addons/sale_order_import_ubl/demo/demo_data.xml
odoo/addons/sale_order_import_ubl/tests/__init__.py
odoo/addons/sale_order_import_ubl/tests/test_ubl_order_import.py
odoo/addons/sale_order_import_ubl/tests/files/UBL-Order-2.0-Example.xml
odoo/addons/sale_order_import_ubl/tests/files/UBL-Order-2.1-Example.xml
odoo/addons/sale_order_import_ubl/tests/files/UBL-RequestForQuotation-2.0-Example.xml
odoo/addons/sale_order_import_ubl/tests/files/UBL-RequestForQuotation-2.1-Example.xml
odoo/addons/sale_order_import_ubl/wizard/__init__.py
odoo/addons/sale_order_import_ubl/wizard/sale_order_import.py
odoo10_addon_sale_order_import_ubl-10.0.1.0.0.dist-info/DESCRIPTION.rst
odoo10_addon_sale_order_import_ubl-10.0.1.0.0.dist-info/METADATA
odoo10_addon_sale_order_import_ubl-10.0.1.0.0.dist-info/RECORD
odoo10_addon_sale_order_import_ubl-10.0.1.0.0.dist-info/WHEEL
odoo10_addon_sale_order_import_ubl-10.0.1.0.0.dist-info/metadata.json
odoo10_addon_sale_order_import_ubl-10.0.1.0.0.dist-info/namespace_packages.txt
odoo10_addon_sale_order_import_ubl-10.0.1.0.0.dist-info/top_level.txt
