Metadata-Version: 2.0
Name: odoo10-addon-sale-order-import-ubl
Version: 10.0.1.0.0
Summary: Import UBL XML sale order files
Home-page: http://www.akretion.com
Author: Akretion,Odoo Community Association (OCA)
Author-email: support@odoo-community.org
License: AGPL-3
Platform: UNKNOWN
Classifier: Programming Language :: Python :: 2.7
Classifier: Framework :: Odoo
Classifier: License :: OSI Approved :: GNU Affero General Public License v3
Requires-Dist: odoo (<10.1dev,>=10.0)
Requires-Dist: odoo10-addon-base-ubl
Requires-Dist: odoo10-addon-sale-order-import
